README.rst
setup.cfg
setup.py
Resource_Helper.egg-info/PKG-INFO
Resource_Helper.egg-info/SOURCES.txt
Resource_Helper.egg-info/dependency_links.txt
Resource_Helper.egg-info/requires.txt
Resource_Helper.egg-info/top_level.txt
resource_helper/__init__.py
resource_helper/resource_consumer.py
resource_helper/resource_manager.py