Metadata-Version: 1.2
Name: Resource-Helper
Version: 0.0.2
Summary: A project that manage resource data
Home-page: https://gitlab.com/heumtax/resource_helper/
Author: jmg7173
Author-email: jmg7173@gmail.com
License: MIT
Platform: UNKNOWN
Classifier: Development Status :: 3 - Alpha
Classifier: Programming Language :: Python :: 3.5
Classifier: Programming Language :: Python :: 3.6
Requires-Python: >=3.5
